{
  "sigma_slope": 0.12010962691144184,
  "sigma_intercept": 0.09874610326560587,
  "sigma_min": 1.4202129970417994,
  "functional_form": "linear",
  "r_squared": 0.8810592926513909,
  "n_bands": 8,
  "note": "sigma_intercept may be negative for a linear fit. Apply: sigma = max(sigma_min, min(sigma_max, sigma_slope * ADP + sigma_intercept)).",
  "diagnostics": {
    "linear_r2": 0.8810592926513909,
    "log_linear_r2": 0.8281690034378093,
    "log_linear_coeffs": {
      "a": 0.7866556444826486,
      "b": -1.2796860274721993
    },
    "bands": [
      {
        "adp_midpoint": 6.0,
        "n_obs": 630305,
        "empirical_sigma": 1.4202129970417994,
        "fitted_sigma": 0.8194038647342569,
        "mean_residual": 0.019481727100372024
      },
      {
        "adp_midpoint": 18.0,
        "n_obs": 645671,
        "empirical_sigma": 2.440588452459529,
        "fitted_sigma": 2.260719387671559,
        "mean_residual": -0.026051162279241306
      },
      {
        "adp_midpoint": 30.0,
        "n_obs": 697311,
        "empirical_sigma": 3.6633377541035173,
        "fitted_sigma": 3.702034910608861,
        "mean_residual": 0.05040657611883361
      },
      {
        "adp_midpoint": 42.0,
        "n_obs": 610278,
        "empirical_sigma": 3.996222388974087,
        "fitted_sigma": 5.143350433546163,
        "mean_residual": -0.7924634183109991
      },
      {
        "adp_midpoint": 54.0,
        "n_obs": 97989,
        "empirical_sigma": 4.633527059434033,
        "fitted_sigma": 6.584665956483465,
        "mean_residual": -5.9371769280225335
      },
      {
        "adp_midpoint": 66.0,
        "n_obs": 5788,
        "empirical_sigma": 8.017845718367688,
        "fitted_sigma": 8.025981479420766,
        "mean_residual": -18.67872149274361
      },
      {
        "adp_midpoint": 78.0,
        "n_obs": 1046,
        "empirical_sigma": 12.768873367681111,
        "fitted_sigma": 9.46729700235807,
        "mean_residual": -41.21003824091778
      },
      {
        "adp_midpoint": 116.44470314318976,
        "n_obs": 1718,
        "empirical_sigma": 13.147721250369099,
        "fitted_sigma": 14.084875953607726,
        "mean_residual": -83.631490104773
      }
    ]
  },
  "position_modifiers": {
    "QB0RB0WR0TE0": {
      "QB": 0.0244,
      "RB": 1.248,
      "WR": 1.1019,
      "TE": 0.0232
    },
    "QB0RB0WR1TE0": {
      "QB": 0.0839,
      "RB": 1.4006,
      "WR": 0.803,
      "TE": 1.8163
    },
    "QB0RB1WR0TE0": {
      "QB": 0.1316,
      "RB": 1.2373,
      "WR": 0.8646,
      "TE": 2.0885
    },
    "QB0RB1WR1TE0": {
      "QB": 2.0742,
      "RB": 0.7309,
      "WR": 0.947,
      "TE": 1.5174
    },
    "QB0RB1WR0TE1": {
      "QB": 2.4593,
      "RB": 0.5295,
      "WR": 1.1503,
      "TE": 0.2626
    },
    "QB0RB0WR2TE0": {
      "QB": 1.715,
      "RB": 1.061,
      "WR": 0.8103,
      "TE": 1.4285
    },
    "QB0RB2WR0TE0": {
      "QB": 2.3407,
      "RB": 0.4538,
      "WR": 1.1049,
      "TE": 1.2466
    },
    "QB0RB0WR3TE0": {
      "QB": 2.4159,
      "RB": 0.9968,
      "WR": 0.7876,
      "TE": 1.0491
    },
    "QB0RB2WR1TE0": {
      "QB": 1.8569,
      "RB": 0.3193,
      "WR": 1.3206,
      "TE": 0.6764
    },
    "QB0RB1WR2TE0": {
      "QB": 2.323,
      "RB": 0.6804,
      "WR": 1.001,
      "TE": 0.9721
    },
    "QB0RB1WR1TE1": {
      "QB": 1.941,
      "RB": 0.5284,
      "WR": 1.2456,
      "TE": 0.0986
    },
    "QB1RB1WR1TE0": {
      "QB": 0.321,
      "RB": 0.7432,
      "WR": 1.2514,
      "TE": 1.0354
    },
    "QB1RB0WR2TE0": {
      "QB": 0.329,
      "RB": 1.2236,
      "WR": 0.9572,
      "TE": 1.0607
    },
    "QB0RB1WR0TE2": {
      "QB": 1.5108,
      "RB": 0.51,
      "WR": 1.295,
      "TE": 0.3267
    },
    "QB1RB1WR0TE1": {
      "QB": 0.3333,
      "RB": 0.4949,
      "WR": 1.4987,
      "TE": 0.1382
    },
    "QB1RB2WR0TE0": {
      "QB": 0.4604,
      "RB": 0.3619,
      "WR": 1.5149,
      "TE": 0.5498
    },
    "QB0RB2WR0TE1": {
      "QB": 1.5964,
      "RB": 0.287,
      "WR": 1.44,
      "TE": 0.1199
    },
    "QB0RB0WR1TE1": {
      "QB": 2.069,
      "RB": 0.9596,
      "WR": 0.9544,
      "TE": 0.2052
    },
    "QB1RB0WR1TE1": {
      "QB": 0.2782,
      "RB": 1.0721,
      "WR": 1.1577,
      "TE": 0.1417
    },
    "QB0RB0WR2TE1": {
      "QB": 2.0227,
      "RB": 0.945,
      "WR": 0.9798,
      "TE": 0.1168
    },
    "QB1RB0WR1TE0": {
      "QB": 1.0765,
      "RB": 1.3145,
      "WR": 0.6205,
      "TE": 2.6138
    },
    "QB0RB3WR0TE0": {
      "QB": 1.6987,
      "RB": 0.281,
      "WR": 1.3884,
      "TE": 0.483
    },
    "QB0RB0WR1TE2": {
      "QB": 1.4654,
      "RB": 0.7585,
      "WR": 1.1683,
      "TE": 0.1754
    },
    "QB1RB1WR0TE0": {
      "QB": 1.3727,
      "RB": 0.7533,
      "WR": 0.982,
      "TE": 2.0152
    },
    "QB1RB0WR0TE0": {
      "QB": 3.7928,
      "RB": 1.0281,
      "WR": 0.5096,
      "TE": 1.5559
    },
    "QB2RB0WR0TE0": {
      "QB": 8.0064,
      "RB": 0.4143,
      "WR": 0.2961,
      "TE": 1.2168
    },
    "QB0RB0WR0TE1": {
      "QB": 0.7102,
      "RB": 1.1074,
      "WR": 0.7819,
      "TE": 2.775
    }
  },
  "stacking_multipliers": {
    "0": 1.0,
    "1": 0.7786,
    "2": 1.0207
  },
  "sigma_max": 4.633527059434033,
  "round_sigma_max": {
    "1": 2.173975390278609,
    "2": 2.9828363592131906,
    "3": 3.5991516595023305,
    "4": 4.081307234389902
  },
  "mu_slope": -1.2552719417228957,
  "mu_intercept": 61.3140465781436,
  "mu_adp_threshold": 54.0,
  "position_sigma_max": {
    "QB": 6.355772443930861,
    "RB": 3.976169576072521,
    "WR": 3.7333202914540515,
    "TE": 3.7999556754460824
  },
  "sigma_max_adp_limit": 116.44470314318976,
  "training_rounds": 4
}